{
    "$schema": "https://json-schema.org/draft/2020-12/schema",
    "$id": "spec/schemas/snapshot.grep.response.schema.json",
    "oneOf": [
        {
            "title": "snapshot.grep worktree success",
            "type": "object",
            "required": [
                "snapshot_id",
                "query",
                "mode",
                "matches",
                "truncated",
                "lease_id",
                "fingerprint",
                "cache_key",
                "cache_hint"
            ],
            "$defs": {
                "line_match": {
                    "type": "object",
                    "required": [
                        "line",
                        "col",
                        "text"
                    ],
                    "properties": {
                        "line": {
                            "type": "integer",
                            "minimum": 1
                        },
                        "col": {
                            "type": "integer",
                            "minimum": 1
                        },
                        "text": {
                            "type": "string"
                        }
                    },
                    "additionalProperties": false
                },
                "file_matches": {
                    "type": "object",
                    "required": [
                        "path",
                        "lines"
                    ],
                    "properties": {
                        "path": {
                            "$ref": "./common.schema.json#/$defs/path"
                        },
                        "lines": {
                            "type": "array",
                            "items": {
                                "$ref": "#/$defs/line_match"
                            }
                        }
                    },
                    "additionalProperties": false
                }
            },
            "properties": {
                "snapshot_id": {
                    "$ref": "./common.schema.json#/$defs/snapshot_id"
                },
                "query": {
                    "type": "string"
                },
                "mode": {
                    "type": "string",
                    "const": "worktree"
                },
                "matches": {
                    "type": "array",
                    "items": {
                        "$ref": "#/$defs/file_matches"
                    }
                },
                "truncated": {
                    "type": "boolean"
                },
                "lease_id": {
                    "$ref": "./common.schema.json#/$defs/lease_id"
                },
                "fingerprint": {
                    "$ref": "./common.schema.json#/$defs/fingerprint"
                },
                "cache_key": {
                    "$ref": "./common.schema.json#/$defs/cache_key"
                },
                "cache_hint": {
                    "type": "string",
                    "const": "until_dirty"
                }
            },
            "additionalProperties": false
        },
        {
            "title": "snapshot.grep snapshot success",
            "type": "object",
            "required": [
                "snapshot_id",
                "query",
                "mode",
                "matches",
                "truncated",
                "cache_key",
                "cache_hint"
            ],
            "properties": {
                "snapshot_id": {
                    "$ref": "./common.schema.json#/$defs/snapshot_id"
                },
                "query": {
                    "type": "string"
                },
                "mode": {
                    "type": "string",
                    "const": "snapshot"
                },
                "matches": {
                    "type": "array",
                    "items": {
                        "$ref": "#/$defs/file_matches"
                    }
                },
                "truncated": {
                    "type": "boolean"
                },
                "cache_key": {
                    "$ref": "./common.schema.json#/$defs/cache_key"
                },
                "cache_hint": {
                    "type": "string",
                    "const": "immutable"
                }
            },
            "additionalProperties": false
        },
        {
            "$ref": "./common.schema.json#/$defs/error"
        }
    ]
}